objconpython.cpython-39-darwin.so
objconpython-0.3.dist-info/METADATA
objconpython-0.3.dist-info/WHEEL
objconpython-0.3.dist-info/top_level.txt
objconpython-0.3.dist-info/RECORD
