Metadata-Version: 2.1
Name: objconpython
Version: 0.3
Summary: A Python package to run objc code on python
Home-page: UNKNOWN
Author: Bobby
Author-email: info@bobby-shop.com
License: UNKNOWN
Platform: UNKNOWN
